[{"names":"Sun","types":"SPECIALSTAR","orbits":"NONE","shapes":"round","color":"orange"},{"names":"Jupiter","types":"Planet","orbits":"4050","shapes":"round","color":"beige"},{"names":"Saturn","types":"Planet","orbits":"10585","shapes":"round","color":"beige"},{"names":"Uranus","types":"Planet","orbits":"30660","shapes":"round","color":"blue"},{"names":"Neptune","types":"Planet","orbits":"59860","shapes":"round","color":"blue"},{"names":"Earth","types":"Planet","orbits":"365","shapes":"round","color":"blue"},{"names":"Venus","types":"Planet","orbits":"222","shapes":"round","color":"grey"},{"names":"Mars","types":"Planet","orbits":"374","shapes":"round","color":"orange"},{"names":"Ganymede","types":"Satellite","orbits":"7","shapes":"round","color":"grey"},{"names":"Titan","types":"Satellite","orbits":"15","shapes":"round","color":"yellow"},{"names":"Mercury","types":"Planet","orbits":"88","shapes":"round","color":"grey"},{"names":"Callisto","types":"Satellite","orbits":"16","shapes":"round","color":"orange"},{"names":"Io","types":"Satellite","orbits":"2","shapes":"round","color":"yellow"},{"names":"Moon","types":"Satellite","orbits":"27","shapes":"round","color":"grey"},{"names":"Europa","types":"Satellite","orbits":"3","shapes":"round","color":"orange"},{"names":"Triton","types":"Satellite","orbits":"6","shapes":"round","color":"grey"},{"names":"Pluto","types":"DwarfPlanet","orbits":"90520","shapes":"round","color":"beige"},{"names":"Eris","types":"DwarfPlanet","orbits":"203305","shapes":"round","color":"grey"},{"names":"Haumea","types":"DwarfPlanet","orbits":"104025","shapes":"round","color":"grey"},{"names":"Titania","types":"Satellite","orbits":"9","shapes":"round","color":"grey"},{"names":"Rhea","types":"Satellite","orbits":"5","shapes":"round","color":"grey"},{"names":"Oberon","types":"Satellite","orbits":"13","shapes":"round","color":"grey"},{"names":"Lapetus","types":"Satellite","orbits":"79","shapes":"round","color":"grey"},{"names":"Makemake","types":"DwarfPlanet","orbits":"112785","shapes":"round","color":"grey"},{"names":"Charon","types":"Satellite","orbits":"6","shapes":"round","color":"grey"},{"names":"Umbriel","types":"Satellite","orbits":"4","shapes":"round","color":"grey"},{"names":"Ariel","types":"Satellite","orbits":"3","shapes":"round","color":"grey"},{"names":"Dione","types":"Satellite","orbits":"3","shapes":"round","color":"grey"},{"names":"Quaoar","types":"Cubewano","orbits":"288","shapes":"unknown","color":"grey"},{"names":"Tethys","types":"Satellite","orbits":"2","shapes":"round","color":"grey"},{"names":"Sedna","types":"Sednoid","orbits":"4401535","shapes":"unknown","color":"grey"},{"names":"Ceres","types":"DwarfPlanet","orbits":"1642","shapes":"round","color":"grey"},{"names":"2002 MS4","types":"Cubewano","orbits":"98915","shapes":"unknown","color":"grey"},{"names":"Orcus","types":"Plutino","orbits":"90155","shapes":"unknown","color":"grey"},{"names":"Salacia","types":"Cubewano","orbits":"100010","shapes":"unknown","color":"grey"},{"names":"Varda","types":"Cubewano","orbits":"114129","shapes":"unknown","color":"grey"},{"names":"Dysnomia","types":"Satellite","orbits":"16","shapes":"unknown","color":"grey"},{"names":"Varuna","types":"Cubewano","orbits":"103295","shapes":"oval","color":"grey"},{"names":"Ixion","types":"Plutino","orbits":"90885","shapes":"round","color":"grey"},{"names":"Vesta","types":"BeltAsteroid","orbits":"1326","shapes":"oval","color":"grey"},{"names":"Pallas","types":"BeltAsteroid","orbits":"1686","shapes":"unknown","color":"grey"},{"names":"Enceladus","types":"Satellite","orbits":"1","shapes":"round","color":"grey"},{"names":"Dziewanna","types":"SDO","orbits":"216416","shapes":"unknown","color":"grey"},{"names":"Vanth","types":"Satellite","orbits":"9","shapes":"round","color":"grey"},{"names":"Miranda","types":"Satellite","orbits":"1","shapes":"round","color":"grey"},{"names":"Huya","types":"Plutino","orbits":"91690","shapes":"unknown","color":"grey"},{"names":"Hygiea","types":"BeltAsteroid","orbits":"2034","shapes":"irregular","color":"grey"},{"names":"Proteus","types":"Satellite","orbits":"1","shapes":"irregular","color":"grey"},{"names":"Mimas","types":"Satellite","orbits":"1","shapes":"round","color":"grey"},{"names":"Nereid","types":"Satellite","orbits":"360","shapes":"irregular","color":"grey"},{"names":"Interamnia","types":"BeltAsteroid","orbits":"1952","shapes":"irregular","color":"grey"},{"names":"Davida","types":"BeltAsteroid","orbits":"2056","shapes":"irregular","color":"grey"},{"names":"Sylvia","types":"BeltAsteroid","orbits":"2382","shapes":"irregular","color":"grey"},{"names":"Actaea","types":"Satellite","orbits":"5","shapes":"irregular","color":"grey"},{"names":"Juno","types":"BeltAsteroid","orbits":"5460","shapes":"irregular","color":"grey"},{"names":"Cybele","types":"BeltAsteroid","orbits":"2319","shapes":"irregular","color":"grey"},{"names":"Hyperion","types":"Satellite","orbits":"21","shapes":"irregular","color":"grey"},{"names":"Eunomia","types":"BeltAsteroid","orbits":"1569","shapes":"irregular","color":"grey"},{"names":"Camilla","types":"BeltAsteroid","orbits":"2383","shapes":"irregular","color":"grey"},{"names":"Euphrosyne","types":"BeltAsteroid","orbits":"2041","shapes":"irregular","color":"grey"},{"names":"Psyche","types":"BeltAsteroid","orbits":"1823","shapes":"irregular","color":"grey"},{"names":"Sila","types":"Cubewano","orbits":"107026","shapes":"irregular","color":"grey"},{"names":"Chariklo","types":"Centaur","orbits":"22987","shapes":"rings","color":"grey"},{"names":"Patientia","types":"BeltAsteroid","orbits":"1956","shapes":"irregular","color":"grey"},{"names":"Bamberga","types":"BeltAsteroid","orbits":"1604","shapes":"irregular","color":"grey"},{"names":"Chiron","types":"Centaur","orbits":"18417","shapes":"rings","color":"grey"},{"names":"Hektor","types":"Satellite","orbits":"4403","shapes":"irregular","color":"grey"},{"names":"Thisbe","types":"BeltAsteroid","orbits":"1681","shapes":"irregular","color":"grey"},{"names":"Ceto","types":"centaur","orbits":"380669","shapes":"irregular","color":"grey"},{"names":"Doris","types":"BeltAsteroid","orbits":"2003","shapes":"irregular","color":"grey"},{"names":"Herculina","types":"BeltAsteroid","orbits":"1687","shapes":"irregular","color":"grey"},{"names":"Eugenia","types":"BeltAsteroid","orbits":"1638","shapes":"irregular","color":"grey"},{"names":"Phoebe","types":"Satellite","orbits":"550","shapes":"irregular","color":"grey"},{"names":"Amphitrite","types":"BeltAsteroid","orbits":"1492","shapes":"irregular","color":"grey"},{"names":"Bienor","types":"Centaur","orbits":"24435","shapes":"irregular","color":"grey"},{"names":"Deucalion","types":"Cubewano","orbits":"108004","shapes":"irregular","color":"grey"},{"names":"Fortuna","types":"BeltAsteroid","orbits":"1393","shapes":"irregular","color":"grey"},{"names":"Egeria","types":"BeltAsteroid","orbits":"1510","shapes":"irregular","color":"grey"},{"names":"Diotima","types":"BeltAsteroid","orbits":"1926","shapes":"irregular","color":"grey"},{"names":"Aurora","types":"BeltAsteroid","orbits":"2051","shapes":"irregular","color":"grey"},{"names":"Themis","types":"BeltAsteroid","orbits":"2021","shapes":"irregular","color":"grey"},{"names":"Iris","types":"BeltAsteroid","orbits":"1345","shapes":"irregular","color":"grey"},{"names":"Daphne","types":"BeltAsteroid","orbits":"1679","shapes":"irregular","color":"grey"},{"names":"Larissa","types":"Satellite","orbits":"2856","shapes":"irregular","color":"grey"},{"names":"Alauda","types":"BeltAsteroid","orbits":"2086","shapes":"irregular","color":"grey"},{"names":"Palma","types":"BeltAsteroid","orbits":"2043","shapes":"irregular","color":"grey"},{"names":"Ursula","types":"BeltAsteroid","orbits":"2016","shapes":"irregular","color":"grey"},{"names":"Aletheia","types":"BeltAsteroid","orbits":"2027","shapes":"irregular","color":"grey"},{"names":"Metis","types":"BeltAsteroid","orbits":"1346","shapes":"irregular","color":"grey"},{"names":"Hermione","types":"BeltAsteroid","orbits":"2338","shapes":"irregular","color":"grey"},{"names":"Bertha","types":"BeltAsteroid","orbits":"2087","shapes":"irregular","color":"grey"},{"names":"Hebe","types":"BeltAsteroid","orbits":"1379","shapes":"irregular","color":"grey"},{"names":"Pholus","types":"Centaur","orbits":"33637","shapes":"irregular","color":"grey"},{"names":"Nemesis","types":"BeltAsteroid","orbits":"1665","shapes":"irregular","color":"grey"},{"names":"Freia","types":"BeltAsteroid","orbits":"2307","shapes":"irregular","color":"grey"},{"names":"Rhadamanthus","types":"Plutino","orbits":"88197","shapes":"irregular","color":"grey"},{"names":"Elektra","types":"BeltAsteroid","orbits":"2021","shapes":"irregular","color":"grey"},{"names":"Kalliope","types":"BeltAsteroid","orbits":"1814","shapes":"irregular","color":"grey"},{"names":"Janus","types":"Satellite","orbits":"1","shapes":"irregular","color":"grey"}]